subdesc-0.2.1.dist-info/METADATA
subdesc-0.2.1.dist-info/WHEEL
subdesc-0.2.1.dist-info/entry_points.txt
subdesc/__init__.py
subdesc/__main__.py
subdesc/cli.py
subdesc/ffsubsync.py
subdesc/mkvmerge.py
subdesc/normalizer.py
subdesc/utils.py
subdesc-0.2.1.dist-info/RECORD
