Metadata-Version: 2.1
Name: subdesc
Version: 0.2.1
Author-Email: AmirMohammad Hosseini Nasab <awmirhn@gmail.com>
License: MIT
Requires-Python: <3.12,>=3.11
Requires-Dist: click>=8.1.7
Requires-Dist: ffsubsync>=0.4.25
Requires-Dist: charset-normalizer>=3.3.0
Requires-Dist: srt>=3.5.3
